lytix_py/__init__.py
lytix_py/colors.py
lytix_py/envVars.py
lytix_py/FastAPIMiddleware/LytixMiddleware.py
lytix_py/FastAPIMiddleware/MiddlewareState.py
lytix_py/LAsyncStore/LAsyncStore.py
lytix_py/LError/LError.py
lytix_py/LError/LErrorIncrement.py
lytix_py/LError/__init__.py
lytix_py/LLogger/LLogger.py
lytix_py/LLogger/LLoggerStreamWrapper.py
lytix_py/Lytix/Lytix.py
lytix_py/Lytix/LytixTest.py
lytix_py/Lytix/RunTestSuite.py
lytix_py/Lytix/TestInstance.py
lytix_py/Lytix/types.py
lytix_py/LytixAsyncLogger/LytixAsyncLogging.py
lytix_py/LytixLangchainCallback/LytixLangchainCallback.py
lytix_py/MetricCollector/MetricCollector.py
lytix_py-4.3.15.dist-info/LICENSE.md
lytix_py-4.3.15.dist-info/METADATA
lytix_py-4.3.15.dist-info/WHEEL
lytix_py-4.3.15.dist-info/top_level.txt
lytix_py-4.3.15.dist-info/RECORD
