Metadata-Version: 2.1
Name: lytix-py
Version: 4.3.15
Summary: Official Lytix Client Packages
Author-email: Lytix <support@lytix.com>
Project-URL: Homepage, https://github.com/Lytix-Labs/lytix-py
Project-URL: Issues, https://github.com/Lytix-Labs/lytix-py/issues
Classifier: Programming Language :: Python :: 3
Classifier: License :: OSI Approved :: MIT License
Classifier: Operating System :: OS Independent
Requires-Python: >=3.8
License-File: LICENSE.md
Requires-Dist: requests==2.31.0
Requires-Dist: urllib3==2.2.1
Requires-Dist: langchain-core<0.4.0,>=0.3.10
Requires-Dist: langchain==0.3.3
Requires-Dist: opentelemetry-api==1.27.0
Requires-Dist: opentelemetry-sdk==1.27.0
Requires-Dist: opentelemetry-exporter-otlp==1.27.0
Requires-Dist: traceloop-sdk==0.33.9
